my_package_matykina_olga/__init__.py
my_package_matykina_olga/__main__.py
my_package_matykina_olga/database.py
my_package_matykina_olga/init0.py
my_package_matykina_olga/init1.py
my_package_matykina_olga/init2.py
my_package_matykina_olga/init3.py
my_package_matykina_olga/init4.py
my_package_matykina_olga/user_management.py
my_package_matykina_olga-0.1.2.dist-info/METADATA
my_package_matykina_olga-0.1.2.dist-info/WHEEL
my_package_matykina_olga-0.1.2.dist-info/top_level.txt
my_package_matykina_olga-0.1.2.dist-info/RECORD
